<?xml version="1.0" encoding="utf-8" ?>
<dwsync>
<file name="Dictionary.php" server="www.peplanning.org.uk//var/www/html/peplanning/" local="130602875930000000" remote="130602875930000000" Dst="2" />
<file name="Object.php" server="www.peplanning.org.uk//var/www/html/peplanning/" local="130602875960000000" remote="130602875960000000" Dst="2" />
<file name="Array.php" server="www.peplanning.org.uk//var/www/html/peplanning/" local="130602875930000000" remote="130602875930000000" Dst="2" />
<file name="Boolean.php" server="www.peplanning.org.uk//var/www/html/peplanning/" local="130602875930000000" remote="130602875930000000" Dst="2" />
<file name="String.php" server="www.peplanning.org.uk//var/www/html/peplanning/" local="130602876000000000" remote="130602876000000000" Dst="2" />
<file name="Stream.php" server="www.peplanning.org.uk//var/www/html/peplanning/" local="130602875980000000" remote="130602875980000000" Dst="2" />
<file name="Null.php" server="www.peplanning.org.uk//var/www/html/peplanning/" local="130602875940000000" remote="130602875940000000" Dst="2" />
<file name="Name.php" server="www.peplanning.org.uk//var/www/html/peplanning/" local="130602875940000000" remote="130602875940000000" Dst="2" />
<file name="Reference.php" server="www.peplanning.org.uk//var/www/html/peplanning/" local="130602875980000000" remote="130602875980000000" Dst="2" />
<file name="Numeric.php" server="www.peplanning.org.uk//var/www/html/peplanning/" local="130602875940000000" remote="130602875940000000" Dst="2" />
</dwsync>